pykit/__init__.py
pykit/__main__.py
pykit/cli.py
pykit/info.py
pykit/scaffolder.py
pykit/templates/README.md.tmpl
pykit/templates/ci_github.yml.tmpl
pykit/templates/fastapi_404.html.tmpl
pykit/templates/fastapi_app_js.tmpl
pykit/templates/fastapi_base.html.tmpl
pykit/templates/fastapi_styles.css.tmpl
pykit/templates/favicon.svg.tmpl
pykit/templates/flask_404.html.tmpl
pykit/templates/flask_app_js.tmpl
pykit/templates/flask_base.html.tmpl
pykit/templates/flask_styles.css.tmpl
pykit/templates/gitignore.tmpl
pykit/templates/licenses.json
pykit/templates/logo.svg.tmpl
pykit/templates/main_app.py.tmpl
pykit/templates/main_cli_stdlib.py.tmpl
pykit/templates/main_cli_typer.py.tmpl
pykit/templates/main_pkg.py.tmpl
pykit/templates/main_web_fastapi.py.tmpl
pykit/templates/main_web_flask.py.tmpl
pykit/templates/pyproject.toml.tmpl
pykitx-1.0.0.dist-info/licenses/LICENSE
pykitx-1.0.0.dist-info/METADATA
pykitx-1.0.0.dist-info/WHEEL
pykitx-1.0.0.dist-info/entry_points.txt
pykitx-1.0.0.dist-info/top_level.txt
pykitx-1.0.0.dist-info/RECORD
